nlp_dataset_readers/__init__.py
nlp_dataset_readers/common/__init__.py
nlp_dataset_readers/common/objects.py
nlp_dataset_readers/common/reader.py
nlp_dataset_readers/semantic_role_labeling/__init__.py
nlp_dataset_readers/semantic_role_labeling/objects.py
nlp_dataset_readers/semantic_role_labeling/srl_readers.py
nlp_dataset_readers/word_in_context/__init__.py
nlp_dataset_readers/word_in_context/wic_readers.py
nlp_dataset_readers/word_sense_disambiguation/__init__.py
nlp_dataset_readers/word_sense_disambiguation/wsd_readers.py
nlp_dataset_readers-0.1.7.dist-info/METADATA
nlp_dataset_readers-0.1.7.dist-info/WHEEL
nlp_dataset_readers-0.1.7.dist-info/top_level.txt
nlp_dataset_readers-0.1.7.dist-info/RECORD
