Metadata-Version: 2.1
Name: nlp-dataset-readers
Version: 0.1.7
Summary: Dataset Readers for NLP
Home-page: https://github.com/Riccorl/nlp-dataset-readers
Author: Riccardo Orlando
Author-email: orlandoricc@gmail.com
License: Apache
Keywords: NLP Sapienza sapienzanlp deep learning transformer pytorch datasets data reader readers dataset
Platform: UNKNOWN
Classifier: Programming Language :: Python :: 3
Classifier: License :: OSI Approved :: Apache Software License
Classifier: Operating System :: OS Independent
Requires-Python: >=3.6
Requires-Dist: conllu
Requires-Dist: rich
